tomba/__init__.py
tomba/__version__.py
tomba/client.py
tomba/exception.py
tomba/service.py
tomba/services/__init__.py
tomba/services/account.py
tomba/services/count.py
tomba/services/domain.py
tomba/services/enrichment.py
tomba/services/finder.py
tomba/services/keys.py
tomba/services/leads_attributes.py
tomba/services/leads_lists.py
tomba/services/logs.py
tomba/services/phone.py
tomba/services/similar.py
tomba/services/sources.py
tomba/services/status.py
tomba/services/technology.py
tomba/services/usage.py
tomba/services/verifier.py
tomba_io-1.0.5.dist-info/LICENSE
tomba_io-1.0.5.dist-info/METADATA
tomba_io-1.0.5.dist-info/WHEEL
tomba_io-1.0.5.dist-info/top_level.txt
tomba_io-1.0.5.dist-info/RECORD
