Metadata-Version: 2.1
Name: tomba-io
Version: 1.0.5
Summary: Tomba.io is an Email Finder for B2B sales and email marketing
Home-page: https://tomba.io
Author: Tomba technology web service LLC
Author-email: info@tomba.io
Maintainer: Mohamed Ben rebia
Maintainer-email: b.mohamed@tomba.io
License: Apache-2.0
Project-URL: Source, https://github.com/tomba-io/python
Project-URL: Tracker, https://github.com/tomba-io/python/issues
Keywords: email,Email Finder,Email Verifier,B2B,Email marketing
Platform: any
Classifier: Development Status :: 5 - Production/Stable
Classifier: Intended Audience :: Developers
Classifier: Environment :: Web Environment
Classifier: Topic :: Software Development
Classifier: Programming Language :: Python :: 3
Classifier: Programming Language :: Python :: 3.5
Classifier: Programming Language :: Python :: 3.6
Classifier: Programming Language :: Python :: 3.7
Classifier: Programming Language :: Python :: 3.8
Requires-Dist: requests
